capturegridbot/__init__.py
capturegridbot/capturegrid.py
capturegridbot/cli.py
capturegridbot/config.py
capturegridbot/events.py
capturegridbot/mounting.py
capturegridbot/service.py
capturegridbot/stats.py
capturegridbot-0.2.0.dist-info/DESCRIPTION.rst
capturegridbot-0.2.0.dist-info/METADATA
capturegridbot-0.2.0.dist-info/RECORD
capturegridbot-0.2.0.dist-info/WHEEL
capturegridbot-0.2.0.dist-info/entry_points.txt
capturegridbot-0.2.0.dist-info/metadata.json
capturegridbot-0.2.0.dist-info/top_level.txt
sharpshooter/__init__.py
sharpshooter/capturegrid.py
sharpshooter/cli.py
sharpshooter/config.py
sharpshooter/events.py
