Metadata-Version: 2.0
Name: capturegridbot
Version: 0.2.0
Summary: Simple automation tool for capture grid
Home-page: https://github.com/ejfitzgerald/capturegridbot
Author: Ed FitzGerald
Author-email: ejafitzgerald@gmail.com
License: UNKNOWN
Keywords: capturegrid
Platform: UNKNOWN
Classifier: Development Status :: 3 - Alpha
Classifier: Intended Audience :: Developers
Classifier: Programming Language :: Python :: 3
Classifier: Programming Language :: Python :: 3.5
Classifier: Programming Language :: Python :: 3.6
Classifier: Programming Language :: Python :: 3.7
Classifier: Programming Language :: Python :: 3.8
Classifier: Programming Language :: Python :: 3 :: Only
Requires-Python: >=3.5, <4
Provides-Extra: dev
Provides-Extra: test
Requires-Dist: pyzmq
Requires-Dist: toml
Provides-Extra: dev
Requires-Dist: check-manifest; extra == 'dev'
Provides-Extra: test
Requires-Dist: coverage; extra == 'test'
